[{"name":"Graue rundliche Katze","beschreibung":"Die Augen glänzen etwas","preis":4.99,"bild":"figurA.png","kategorie":"neuheiten"},
{"name":"unfertige Katzen-Figur","beschreibung":"(verflucht!)","preis":6.66,"bild":"figurB.png","kategorie":"angebote"},{"name":"unfertige Katzen-Figur 2","beschreibung":"Eine schlafende Katze (nicht verflucht)","preis":2.69,"bild":"figurC.png","kategorie":"angebote"},
{"name":"Schleich Katze laufend","beschreibung":"Eine laufende Katze","preis":11.99,"bild":"figur1.png","kategorie":"figuren"},{"name":"Schleich Katze stehend","beschreibung":"Eine stehende Katze","preis":9.99,"bild":"figur2.png","kategorie":"figuren"},{"name":"Schleich Katze sitzend","beschreibung":"Eine sitzende Katze","preis":9.99,"bild":"figur3.png","kategorie":"figuren"},{"name":"Schleich Katze putzend","beschreibung":"Eine sich putzende Katze","preis":6.99,"bild":"figur4.png","kategorie":"figuren"},{"name":"Schleich Katze streckend","beschreibung":"Eine sich streckende Katze","preis":6.99,"bild":"figur5.png","kategorie":"figuren"},{"name":"Schleich spielende Kätzchen","beschreibung":"Kätzchen, die spielen","preis":8.99,"bild":"figur6.png","kategorie":"figuren"},{"name":"Schleich spielende Kätzchen 2","beschreibung":"schon wieder","preis":8.99,"bild":"figur7.png","kategorie":"figuren"},{"name":"Schleich Maine-Coon-Katze","beschreibung":"Eine stehende Langhaarkatze","preis":3.99,"bild":"figur8.png","kategorie":"figuren"},{"name":"Schleich schauende Katze","beschreibung":"[originelle Beschreibung]","preis":3.99,"bild":"figur9.png","kategorie":"figuren"},
{"name":"Plüsch-Katzen-Anhänger","beschreibung":"Mit Reißverschluss!","preis":4.99,"bild":"pluesch1.png","kategorie":"plueschtiere"},{"name":"FurReal friends Samtpfötchen","beschreibung":"Schläft schon seit Jahren. Funktioniert noch!","preis":99.99,"bild":"pluesch2.png","kategorie":"plueschtiere"},
{"name":"Katzen-Kerze","beschreibung":"Echte Bienenwachs-Kerze in Katzenform","preis":14.99,"bild":"kerze.png","kategorie":"sonstiges"}]